sphinx_to_jekyll/__init__.py
sphinx_to_jekyll/jekyll_builder.py
sphinx_to_jekyll/jekyll_writer.py
sphinx_to_jekyll-0.0.2.dist-info/LICENSE
sphinx_to_jekyll-0.0.2.dist-info/METADATA
sphinx_to_jekyll-0.0.2.dist-info/WHEEL
sphinx_to_jekyll-0.0.2.dist-info/entry_points.txt
sphinx_to_jekyll-0.0.2.dist-info/top_level.txt
sphinx_to_jekyll-0.0.2.dist-info/RECORD
