Metadata-Version: 2.1
Name: sphinx-to-jekyll
Version: 0.0.2
Summary: Generate jekyll markdown with frontmatter from sphinx documentation
Home-page: https://github.com/codejamninja/sphinx-to-jekyll
Author: Jam Risser
Author-email: jam@codejam.ninja
License: MIT
Keywords: sphinx jekyll docs documentation frontmatter markdown
Platform: UNKNOWN
Classifier: Development Status :: 4 - Beta
Classifier: Intended Audience :: Developers
Classifier: Topic :: Utilities
Classifier: License :: OSI Approved :: MIT License
Classifier: Programming Language :: Python :: 2
Classifier: Programming Language :: Python :: 2.7
Classifier: Programming Language :: Python :: 3
Classifier: Programming Language :: Python :: 3.3
Classifier: Programming Language :: Python :: 3.4
Classifier: Programming Language :: Python :: 3.5
Requires-Dist: alabaster (==0.7.12)
Requires-Dist: Babel (==2.6.0)
Requires-Dist: certifi (==2018.10.15)
Requires-Dist: chardet (==3.0.4)
Requires-Dist: docutils (==0.14)
Requires-Dist: idna (==2.7)
Requires-Dist: imagesize (==1.1.0)
Requires-Dist: Jinja2 (==2.10)
Requires-Dist: MarkupSafe (==1.1.0)
Requires-Dist: packaging (==18.0)
Requires-Dist: Pygments (==2.2.0)
Requires-Dist: pyparsing (==2.3.0)
Requires-Dist: pytz (==2018.7)
Requires-Dist: requests (==2.20.1)
Requires-Dist: six (==1.11.0)
Requires-Dist: snowballstemmer (==1.2.1)
Requires-Dist: Sphinx (==1.8.1)
Requires-Dist: sphinxcontrib-websupport (==1.1.0)
Requires-Dist: typing (==3.6.6)
Requires-Dist: urllib3 (==1.24.1)
